odoo/addons/account_payment_partner/README.rst
odoo/addons/account_payment_partner/__init__.py
odoo/addons/account_payment_partner/__manifest__.py
odoo/addons/account_payment_partner/hooks.py
odoo/addons/account_payment_partner/demo/partner_demo.xml
odoo/addons/account_payment_partner/i18n/account_payment_partner.pot
odoo/addons/account_payment_partner/i18n/ca.po
odoo/addons/account_payment_partner/i18n/da_DK.po
odoo/addons/account_payment_partner/i18n/de.po
odoo/addons/account_payment_partner/i18n/es.po
odoo/addons/account_payment_partner/i18n/es_AR.po
odoo/addons/account_payment_partner/i18n/es_CL.po
odoo/addons/account_payment_partner/i18n/fr.po
odoo/addons/account_payment_partner/i18n/fr_FR.po
odoo/addons/account_payment_partner/i18n/hr.po
odoo/addons/account_payment_partner/i18n/it.po
odoo/addons/account_payment_partner/i18n/lv.po
odoo/addons/account_payment_partner/i18n/nb_NO.po
odoo/addons/account_payment_partner/i18n/nl.po
odoo/addons/account_payment_partner/i18n/pt.po
odoo/addons/account_payment_partner/i18n/pt_BR.po
odoo/addons/account_payment_partner/i18n/sl.po
odoo/addons/account_payment_partner/i18n/sv.po
odoo/addons/account_payment_partner/i18n/tr.po
odoo/addons/account_payment_partner/migrations/18.0.1.0.0/post-migration.py
odoo/addons/account_payment_partner/models/__init__.py
odoo/addons/account_payment_partner/models/account_move.py
odoo/addons/account_payment_partner/models/account_move_line.py
odoo/addons/account_payment_partner/models/account_payment_mode.py
odoo/addons/account_payment_partner/models/res_partner.py
odoo/addons/account_payment_partner/readme/CONTRIBUTORS.md
odoo/addons/account_payment_partner/readme/DESCRIPTION.md
odoo/addons/account_payment_partner/readme/HISTORY.md
odoo/addons/account_payment_partner/readme/USAGE.md
odoo/addons/account_payment_partner/reports/__init__.py
odoo/addons/account_payment_partner/reports/account_invoice_report.py
odoo/addons/account_payment_partner/reports/account_invoice_report_view.xml
odoo_addon_account_payment_partner-18.0.1.0.2.3.dist-info/METADATA
odoo_addon_account_payment_partner-18.0.1.0.2.3.dist-info/WHEEL
odoo_addon_account_payment_partner-18.0.1.0.2.3.dist-info/top_level.txt
odoo_addon_account_payment_partner-18.0.1.0.2.3.dist-info/RECORD
