Metadata-Version: 2.1
Name: odoo-addon-account_payment_partner
Version: 18.0.1.0.2.3
Requires-Python: >=3.10
Requires-Dist: odoo-addon-account_payment_mode==18.0.*
Requires-Dist: odoo==18.0.*
Summary: Adds payment mode on partners and invoices
Home-page: https://github.com/OCA/bank-payment
License: AGPL-3
Author: Akretion, Tecnativa, Odoo Community Association (OCA)
Author-email: support@odoo-community.org
Classifier: Programming Language :: Python
Classifier: Framework :: Odoo
Classifier: Framework :: Odoo :: 18.0
Classifier: License :: OSI Approved :: GNU Affero General Public License v3
Classifier: Development Status :: 6 - Mature
